{
  "collectionName": "components_sections_heroes",
  "info": {
    "displayName": "Hero",
    "description": ""
  },
  "options": {},
  "attributes": {
    "isShow": {
      "type": "boolean",
      "default": true
    },
    "heroText": {
      "type": "richtext"
    },
    "heroImage": {
      "type": "media",
      "multiple": false,
      "required": false,
      "allowedTypes": [
        "images"
      ]
    },
    "ctas": {
      "type": "component",
      "repeatable": true,
      "component": "components.cta"
    }
  }
}
